{
	"info": {
		"_postman_id": "d165e1cc-a6ba-494d-9c3d-bd320de8f8e9",
		"name": "FinalYearProject",
		"schema": "https://schema.getpostman.com/json/collection/v2.1.0/collection.json"
	},
	"item": [
		{
			"name": "Database",
			"item": [
				{
					"name": "GET TableNames",
					"protocolProfileBehavior": {
						"disableBodyPruning": true
					},
					"request": {
						"method": "GET",
						"header": [
							{
								"key": "Content-Type",
								"name": "Content-Type",
								"value": "application/json",
								"type": "text"
							}
						],
						"body": {
							"mode": "raw",
							"raw": "{\n\"item\": \"annualsecuritycost\"\n}"
						},
						"url": {
							"raw": "http://localhost:3000/data/",
							"protocol": "http",
							"host": [
								"localhost"
							],
							"port": "3000",
							"path": [
								"data",
								""
							]
						}
					},
					"response": []
				},
				{
					"name": "GET TableValues",
					"protocolProfileBehavior": {
						"disableBodyPruning": true
					},
					"request": {
						"method": "GET",
						"header": [
							{
								"key": "Content-Type",
								"name": "Content-Type",
								"value": "application/json",
								"type": "text"
							}
						],
						"body": {
							"mode": "raw",
							"raw": ""
						},
						"url": {
							"raw": "http://localhost:3000/data/link?item=annualsecuritycost",
							"protocol": "http",
							"host": [
								"localhost"
							],
							"port": "3000",
							"path": [
								"data",
								"link"
							],
							"query": [
								{
									"key": "item",
									"value": "annualsecuritycost"
								}
							]
						}
					},
					"response": []
				},
				{
					"name": "PUT update table",
					"request": {
						"method": "PUT",
						"header": [
							{
								"key": "Content-Type",
								"value": "application/json",
								"type": "text"
							}
						],
						"body": {
							"mode": "raw",
							"raw": "{ \"table_name\": \"bus\", \"id\": \"2\", \"bus_name\": \"AES-LALP\", \"bus_code\": \"85\" }"
						},
						"url": {
							"raw": "http://localhost:3000/update/edit",
							"protocol": "http",
							"host": [
								"localhost"
							],
							"port": "3000",
							"path": [
								"update",
								"edit"
							]
						}
					},
					"response": []
				},
				{
					"name": "DELETE TableRow",
					"request": {
						"method": "DELETE",
						"header": [
							{
								"key": "Content-Type",
								"name": "Content-Type",
								"value": "application/json",
								"type": "text"
							}
						],
						"body": {
							"mode": "raw",
							"raw": "{ \"table_name\": \"bus\", \"id\": \"2\", \"bus_name\": \"AES-LALP\", \"bus_code\": \"85\" }"
						},
						"url": {
							"raw": "http://localhost:3000/update/delete",
							"protocol": "http",
							"host": [
								"localhost"
							],
							"port": "3000",
							"path": [
								"update",
								"delete"
							]
						}
					},
					"response": []
				},
				{
					"name": "POST InsterRowInTable",
					"request": {
						"method": "POST",
						"header": [
							{
								"key": "Content-Type",
								"value": "application/json",
								"type": "text"
							}
						],
						"body": {
							"mode": "raw",
							"raw": "{ \"table_name\": \"bus\", \"id\": \"200\", \"bus_name\": \"AES-LALP\", \"bus_code\": \"85\" }"
						},
						"url": {
							"raw": "http://localhost:3000/update/insert",
							"protocol": "http",
							"host": [
								"localhost"
							],
							"port": "3000",
							"path": [
								"update",
								"insert"
							]
						}
					},
					"response": []
				}
			],
			"protocolProfileBehavior": {}
		},
		{
			"name": "EPP&CPP Computations",
			"item": [
				{
					"name": "POST Send Assumptions",
					"request": {
						"method": "POST",
						"header": [
							{
								"key": "Content-Type",
								"value": "application/json",
								"type": "text"
							}
						],
						"body": {
							"mode": "raw",
							"raw": "{\n    \"year\": \"2020\",\n    \"assumption\": [\n        [\n            \"2020-01-01T00:00:00.000Z\",\n            {\n                \"dollar_parity\": \"45\",\n                \"us_cpi\": \"123\",\n                \"local_cpi\": \"135\",\n                \"kibor\": \"0\",\n                \"libor\": \"0\",\n                \"sinsoure_fee\": \"0\"\n            }\n        ],\n        [\n            \"2020-02-01T00:00:00.000Z\",\n            {\n                \"dollar_parity\": \"35\",\n                \"us_cpi\": \"131\",\n                \"local_cpi\": \"113\",\n                \"kibor\": \"0\",\n                \"libor\": \"0\",\n                \"sinsoure_fee\": \"0\"\n            }\n        ]\n    ]\n}"
						},
						"url": {
							"raw": "http://localhost:4000/submit/",
							"protocol": "http",
							"host": [
								"localhost"
							],
							"port": "4000",
							"path": [
								"submit",
								""
							]
						}
					},
					"response": []
				}
			],
			"protocolProfileBehavior": {}
		},
		{
			"name": "FCC Computations",
			"item": [
				{
					"name": "POST Send FCC assumptions",
					"request": {
						"method": "POST",
						"header": [
							{
								"key": "Content-Type",
								"value": "application/json",
								"type": "text"
							}
						],
						"body": {
							"mode": "raw",
							"raw": "{\n    \"year\": \"2020\",\n    \"assumption\": [\n        [\n            \"2020-01-01T00:00:00.000Z\",\n            {\n                \"gas\": \"122\",\n                \"rlng\": \"225\",\n                \"thar_oal\": \"330\",\n                \"imp_coal\": \"17\",\n                \"rfo\": \"120\",\n                \"hsd\": \"650\",\n                \"baggase\": \"18\",\n                \"liberty_1\": \"1503.43\",\n                \"uch_1\": \"916.683\",\n                \"rlng_new\": \"1400\",\n                \"imported_iran\": \"1\",\n                \"nuclear\": \"1\",\n                \"mix_cap\": \"1\",\n\t\t\t\t\"local_coal_calorific_value\": \"1\",\n                \"import_coal_calorific_value\": \"1\"\n            }\n        ],\n        [\n            \"2020-02-01T00:00:00.000Z\",\n            {\n                \"gas\": \"152\",\n                \"rlng\": \"215\",\n                \"thar_oal\": \"310\",\n                \"imp_coal\": \"17\",\n                \"rfo\": \"120\",\n                \"hsd\": \"650\",\n                \"baggase\": \"18\",\n                \"liberty_1\": \"1503.43\",\n                \"uch_1\": \"916.683\",\n                \"rlng_new\": \"1400\",\n                \"imported_iran\": \"1\",\n                \"nuclear\": \"1\",\n                \"mix_cap\": \"1\",\n\t\t\t\t\"local_coal_calorific_value\": \"1\",\n                \"import_coal_calorific_value\": \"1\"\n            }\n        ]\n    ]\n}"
						},
						"url": {
							"raw": "http://localhost:4000/submitFCC/",
							"protocol": "http",
							"host": [
								"localhost"
							],
							"port": "4000",
							"path": [
								"submitFCC",
								""
							]
						}
					},
					"response": []
				}
			],
			"protocolProfileBehavior": {}
		},
		{
			"name": "Authentication",
			"item": [],
			"protocolProfileBehavior": {}
		},
		{
			"name": "Visualization",
			"item": [],
			"protocolProfileBehavior": {}
		},
		{
			"name": "SDDP",
			"item": [
				{
					"name": "GET ResultsFromDatabase",
					"protocolProfileBehavior": {
						"disableBodyPruning": true
					},
					"request": {
						"method": "GET",
						"header": [
							{
								"key": "Content-Type",
								"value": "application/json",
								"type": "text"
							}
						],
						"body": {
							"mode": "raw",
							"raw": ""
						},
						"url": {
							"raw": "http://localhost:4000/results/?id=4",
							"protocol": "http",
							"host": [
								"localhost"
							],
							"port": "4000",
							"path": [
								"results",
								""
							],
							"query": [
								{
									"key": "id",
									"value": "4"
								}
							]
						}
					},
					"response": []
				}
			],
			"protocolProfileBehavior": {}
		}
	],
	"protocolProfileBehavior": {}
}